README.md
setup.py
flattentei/__init__.py
flattentei/extract_parts.py
flattentei/flatten_tei_folder.py
flattentei/loader.py
flattentei/tei_to_text_and_standoff.py
flattentei.egg-info/PKG-INFO
flattentei.egg-info/SOURCES.txt
flattentei.egg-info/dependency_links.txt
flattentei.egg-info/entry_points.txt
flattentei.egg-info/requires.txt
flattentei.egg-info/top_level.txt