Metadata-Version: 2.1
Name: flattentei
Version: 0.1.7
Summary: Transform tei xml to a simple standoff format
Home-page: https://github.com/ottowg/flatten-tei
Author: Wolf Otto
Author-email: wolfgang.otto@gesis.org
License: BSD 2-clause
Platform: UNKNOWN
Classifier: Development Status :: 1 - Planning
Classifier: Intended Audience :: Science/Research
Classifier: License :: OSI Approved :: BSD License
Classifier: Operating System :: POSIX :: Linux
Classifier: Programming Language :: Python :: 3
Classifier: Programming Language :: Python :: 3.9
